SegmentAnyConfocal/SegmentAnyConfocal.py
SegmentAnyConfocal/__init__.py
frangi_filter/__init__.py
frangi_filter/frangi_filter.py
frangi_filter/gaussian_smoothing.py
segment_any_confocal_images/__init__.py
segment_any_confocal_images/_reader.py
segment_any_confocal_images/_sample_data.py
segment_any_confocal_images/_version.py
segment_any_confocal_images/_widget.py
segment_any_confocal_images/_writer.py
segment_any_confocal_images/napari.yaml
segment_any_confocal_images/_tests/__init__.py
segment_any_confocal_images/_tests/test_reader.py
segment_any_confocal_images/_tests/test_sample_data.py
segment_any_confocal_images/_tests/test_widget.py
segment_any_confocal_images/_tests/test_writer.py
segment_any_confocal_images-0.0.7.dist-info/licenses/LICENSE
segment_any_confocal_images-0.0.7.dist-info/METADATA
segment_any_confocal_images-0.0.7.dist-info/WHEEL
segment_any_confocal_images-0.0.7.dist-info/entry_points.txt
segment_any_confocal_images-0.0.7.dist-info/top_level.txt
segment_any_confocal_images-0.0.7.dist-info/RECORD
