Metadata-Version: 2.4
Name: segment-any-confocal-images
Version: 0.0.7
Summary: Segment Any Confocal Images is a flexible and high-performance plugin designed for segmentation of confocal microscopy data. It supports both 2D and 3D image stacks, enabling users to identify and extract cellular or subcellular structures with minimal manual effort.
Author: Huibao Feng
Author-email: fenghuibao@gmail.com
License: <<<<<<< HEAD
Classifier: Development Status :: 2 - Pre-Alpha
Classifier: Framework :: napari
Classifier: Intended Audience :: Developers
Classifier: License :: OSI Approved :: MIT License
Classifier: Operating System :: OS Independent
Classifier: Programming Language :: Python
Classifier: Programming Language :: Python :: 3
Classifier: Programming Language :: Python :: 3 :: Only
Classifier: Programming Language :: Python :: 3.10
Classifier: Programming Language :: Python :: 3.11
Classifier: Programming Language :: Python :: 3.12
Classifier: Programming Language :: Python :: 3.13
Classifier: Topic :: Scientific/Engineering :: Image Processing
Requires-Python: >=3.10
License-File: LICENSE
Requires-Dist: numpy
Requires-Dist: magicgui
Requires-Dist: qtpy
Requires-Dist: scikit-image
Provides-Extra: all
Requires-Dist: napari[all]; extra == "all"
Dynamic: license-file
